{
  "openapi": "3.1.0",
  "info": {
    "title": "LifeOS API",
    "version": "0.1.0"
  },
  "paths": {
    "/v1/users": {
      "get": {
        "tags": [
          "users"
        ],
        "summary": "List Users",
        "operationId": "list_users_v1_users_get",
        "parameters": [
          {
            "name": "page",
            "in": "query",
            "required": false,
            "schema": {
              "type": "integer",
              "minimum": 1,
              "default": 1,
              "title": "Page"
            }
          },
          {
            "name": "size",
            "in": "query",
            "required": false,
            "schema": {
              "type": "integer",
              "maximum": 100,
              "default": 20,
              "title": "Size"
            }
          },
          {
            "name": "authorization",
            "in": "header",
            "required": false,
            "schema": {
              "anyOf": [
                {
                  "type": "string"
                },
                {
                  "type": "null"
                }
              ],
              "title": "Authorization"
            }
          }
        ],
        "responses": {
          "200": {
            "description": "Successful Response",
            "content": {
              "application/json": {
                "schema": {
                  "$ref": "#/components/schemas/PaginatedUsers"
                }
              }
            }
          },
          "422": {
            "description": "Validation Error",
            "content": {
              "application/json": {
                "schema": {
                  "$ref": "#/components/schemas/HTTPValidationError"
                }
              }
            }
          }
        }
      }
    },
    "/v1/users/{id}": {
      "get": {
        "tags": [
          "users"
        ],
        "summary": "Get User",
        "operationId": "get_user_v1_users__id__get",
        "parameters": [
          {
            "name": "id",
            "in": "path",
            "required": true,
            "schema": {
              "type": "integer",
              "title": "Id"
            }
          },
          {
            "name": "authorization",
            "in": "header",
            "required": false,
            "schema": {
              "anyOf": [
                {
                  "type": "string"
                },
                {
                  "type": "null"
                }
              ],
              "title": "Authorization"
            }
          }
        ],
        "responses": {
          "200": {
            "description": "Successful Response",
            "content": {
              "application/json": {
                "schema": {
                  "$ref": "#/components/schemas/User"
                }
              }
            }
          },
          "422": {
            "description": "Validation Error",
            "content": {
              "application/json": {
                "schema": {
                  "$ref": "#/components/schemas/HTTPValidationError"
                }
              }
            }
          }
        }
      },
      "put": {
        "tags": [
          "users"
        ],
        "summary": "Update User",
        "operationId": "update_user_v1_users__id__put",
        "parameters": [
          {
            "name": "id",
            "in": "path",
            "required": true,
            "schema": {
              "type": "integer",
              "title": "Id"
            }
          },
          {
            "name": "authorization",
            "in": "header",
            "required": false,
            "schema": {
              "anyOf": [
                {
                  "type": "string"
                },
                {
                  "type": "null"
                }
              ],
              "title": "Authorization"
            }
          }
        ],
        "requestBody": {
          "required": true,
          "content": {
            "application/json": {
              "schema": {
                "$ref": "#/components/schemas/UserUpdate"
              }
            }
          }
        },
        "responses": {
          "200": {
            "description": "Successful Response",
            "content": {
              "application/json": {
                "schema": {
                  "$ref": "#/components/schemas/User"
                }
              }
            }
          },
          "422": {
            "description": "Validation Error",
            "content": {
              "application/json": {
                "schema": {
                  "$ref": "#/components/schemas/HTTPValidationError"
                }
              }
            }
          }
        }
      },
      "delete": {
        "tags": [
          "users"
        ],
        "summary": "Delete User",
        "operationId": "delete_user_v1_users__id__delete",
        "parameters": [
          {
            "name": "id",
            "in": "path",
            "required": true,
            "schema": {
              "type": "integer",
              "title": "Id"
            }
          },
          {
            "name": "authorization",
            "in": "header",
            "required": false,
            "schema": {
              "anyOf": [
                {
                  "type": "string"
                },
                {
                  "type": "null"
                }
              ],
              "title": "Authorization"
            }
          }
        ],
        "responses": {
          "200": {
            "description": "Successful Response",
            "content": {
              "application/json": {
                "schema": {
                  "type": "object",
                  "additionalProperties": true,
                  "title": "Response Delete User V1 Users  Id  Delete"
                }
              }
            }
          },
          "422": {
            "description": "Validation Error",
            "content": {
              "application/json": {
                "schema": {
                  "$ref": "#/components/schemas/HTTPValidationError"
                }
              }
            }
          }
        }
      }
    },
    "/v1/courses": {
      "get": {
        "tags": [
          "courses"
        ],
        "summary": "List Courses",
        "operationId": "list_courses_v1_courses_get",
        "parameters": [
          {
            "name": "page",
            "in": "query",
            "required": false,
            "schema": {
              "type": "integer",
              "minimum": 1,
              "default": 1,
              "title": "Page"
            }
          },
          {
            "name": "size",
            "in": "query",
            "required": false,
            "schema": {
              "type": "integer",
              "maximum": 100,
              "default": 20,
              "title": "Size"
            }
          },
          {
            "name": "authorization",
            "in": "header",
            "required": false,
            "schema": {
              "anyOf": [
                {
                  "type": "string"
                },
                {
                  "type": "null"
                }
              ],
              "title": "Authorization"
            }
          }
        ],
        "responses": {
          "200": {
            "description": "Successful Response",
            "content": {
              "application/json": {
                "schema": {
                  "$ref": "#/components/schemas/PaginatedCourses"
                }
              }
            }
          },
          "422": {
            "description": "Validation Error",
            "content": {
              "application/json": {
                "schema": {
                  "$ref": "#/components/schemas/HTTPValidationError"
                }
              }
            }
          }
        }
      },
      "post": {
        "tags": [
          "courses"
        ],
        "summary": "Create Course",
        "operationId": "create_course_v1_courses_post",
        "parameters": [
          {
            "name": "authorization",
            "in": "header",
            "required": false,
            "schema": {
              "anyOf": [
                {
                  "type": "string"
                },
                {
                  "type": "null"
                }
              ],
              "title": "Authorization"
            }
          }
        ],
        "requestBody": {
          "required": true,
          "content": {
            "application/json": {
              "schema": {
                "$ref": "#/components/schemas/CourseCreate"
              }
            }
          }
        },
        "responses": {
          "201": {
            "description": "Successful Response",
            "content": {
              "application/json": {
                "schema": {
                  "$ref": "#/components/schemas/Course"
                }
              }
            }
          },
          "422": {
            "description": "Validation Error",
            "content": {
              "application/json": {
                "schema": {
                  "$ref": "#/components/schemas/HTTPValidationError"
                }
              }
            }
          }
        }
      }
    },
    "/v1/courses/{id}": {
      "get": {
        "tags": [
          "courses"
        ],
        "summary": "Get Course",
        "operationId": "get_course_v1_courses__id__get",
        "parameters": [
          {
            "name": "id",
            "in": "path",
            "required": true,
            "schema": {
              "type": "integer",
              "title": "Id"
            }
          },
          {
            "name": "authorization",
            "in": "header",
            "required": false,
            "schema": {
              "anyOf": [
                {
                  "type": "string"
                },
                {
                  "type": "null"
                }
              ],
              "title": "Authorization"
            }
          }
        ],
        "responses": {
          "200": {
            "description": "Successful Response",
            "content": {
              "application/json": {
                "schema": {
                  "$ref": "#/components/schemas/Course"
                }
              }
            }
          },
          "422": {
            "description": "Validation Error",
            "content": {
              "application/json": {
                "schema": {
                  "$ref": "#/components/schemas/HTTPValidationError"
                }
              }
            }
          }
        }
      },
      "put": {
        "tags": [
          "courses"
        ],
        "summary": "Update Course",
        "operationId": "update_course_v1_courses__id__put",
        "parameters": [
          {
            "name": "id",
            "in": "path",
            "required": true,
            "schema": {
              "type": "integer",
              "title": "Id"
            }
          },
          {
            "name": "authorization",
            "in": "header",
            "required": false,
            "schema": {
              "anyOf": [
                {
                  "type": "string"
                },
                {
                  "type": "null"
                }
              ],
              "title": "Authorization"
            }
          }
        ],
        "requestBody": {
          "required": true,
          "content": {
            "application/json": {
              "schema": {
                "$ref": "#/components/schemas/CourseUpdate"
              }
            }
          }
        },
        "responses": {
          "200": {
            "description": "Successful Response",
            "content": {
              "application/json": {
                "schema": {
                  "$ref": "#/components/schemas/Course"
                }
              }
            }
          },
          "422": {
            "description": "Validation Error",
            "content": {
              "application/json": {
                "schema": {
                  "$ref": "#/components/schemas/HTTPValidationError"
                }
              }
            }
          }
        }
      },
      "delete": {
        "tags": [
          "courses"
        ],
        "summary": "Delete Course",
        "operationId": "delete_course_v1_courses__id__delete",
        "parameters": [
          {
            "name": "id",
            "in": "path",
            "required": true,
            "schema": {
              "type": "integer",
              "title": "Id"
            }
          },
          {
            "name": "authorization",
            "in": "header",
            "required": false,
            "schema": {
              "anyOf": [
                {
                  "type": "string"
                },
                {
                  "type": "null"
                }
              ],
              "title": "Authorization"
            }
          }
        ],
        "responses": {
          "200": {
            "description": "Successful Response",
            "content": {
              "application/json": {
                "schema": {
                  "type": "object",
                  "additionalProperties": true,
                  "title": "Response Delete Course V1 Courses  Id  Delete"
                }
              }
            }
          },
          "422": {
            "description": "Validation Error",
            "content": {
              "application/json": {
                "schema": {
                  "$ref": "#/components/schemas/HTTPValidationError"
                }
              }
            }
          }
        }
      }
    },
    "/v1/assesments": {
      "get": {
        "tags": [
          "assesments"
        ],
        "summary": "List Assesments",
        "operationId": "list_assesments_v1_assesments_get",
        "parameters": [
          {
            "name": "page",
            "in": "query",
            "required": false,
            "schema": {
              "type": "integer",
              "minimum": 1,
              "default": 1,
              "title": "Page"
            }
          },
          {
            "name": "size",
            "in": "query",
            "required": false,
            "schema": {
              "type": "integer",
              "maximum": 100,
              "default": 20,
              "title": "Size"
            }
          },
          {
            "name": "authorization",
            "in": "header",
            "required": false,
            "schema": {
              "anyOf": [
                {
                  "type": "string"
                },
                {
                  "type": "null"
                }
              ],
              "title": "Authorization"
            }
          }
        ],
        "responses": {
          "200": {
            "description": "Successful Response",
            "content": {
              "application/json": {
                "schema": {
                  "$ref": "#/components/schemas/PaginatedAssesments"
                }
              }
            }
          },
          "422": {
            "description": "Validation Error",
            "content": {
              "application/json": {
                "schema": {
                  "$ref": "#/components/schemas/HTTPValidationError"
                }
              }
            }
          }
        }
      },
      "post": {
        "tags": [
          "assesments"
        ],
        "summary": "Create Assesment",
        "operationId": "create_assesment_v1_assesments_post",
        "parameters": [
          {
            "name": "authorization",
            "in": "header",
            "required": false,
            "schema": {
              "anyOf": [
                {
                  "type": "string"
                },
                {
                  "type": "null"
                }
              ],
              "title": "Authorization"
            }
          }
        ],
        "requestBody": {
          "required": true,
          "content": {
            "application/json": {
              "schema": {
                "$ref": "#/components/schemas/AssesmentCreate"
              }
            }
          }
        },
        "responses": {
          "201": {
            "description": "Successful Response",
            "content": {
              "application/json": {
                "schema": {
                  "$ref": "#/components/schemas/Assesment"
                }
              }
            }
          },
          "422": {
            "description": "Validation Error",
            "content": {
              "application/json": {
                "schema": {
                  "$ref": "#/components/schemas/HTTPValidationError"
                }
              }
            }
          }
        }
      }
    },
    "/v1/assesments/{id}": {
      "get": {
        "tags": [
          "assesments"
        ],
        "summary": "Get Assesment",
        "operationId": "get_assesment_v1_assesments__id__get",
        "parameters": [
          {
            "name": "id",
            "in": "path",
            "required": true,
            "schema": {
              "type": "integer",
              "title": "Id"
            }
          },
          {
            "name": "authorization",
            "in": "header",
            "required": false,
            "schema": {
              "anyOf": [
                {
                  "type": "string"
                },
                {
                  "type": "null"
                }
              ],
              "title": "Authorization"
            }
          }
        ],
        "responses": {
          "200": {
            "description": "Successful Response",
            "content": {
              "application/json": {
                "schema": {
                  "$ref": "#/components/schemas/Assesment"
                }
              }
            }
          },
          "422": {
            "description": "Validation Error",
            "content": {
              "application/json": {
                "schema": {
                  "$ref": "#/components/schemas/HTTPValidationError"
                }
              }
            }
          }
        }
      },
      "put": {
        "tags": [
          "assesments"
        ],
        "summary": "Update Assesment",
        "operationId": "update_assesment_v1_assesments__id__put",
        "parameters": [
          {
            "name": "id",
            "in": "path",
            "required": true,
            "schema": {
              "type": "integer",
              "title": "Id"
            }
          },
          {
            "name": "authorization",
            "in": "header",
            "required": false,
            "schema": {
              "anyOf": [
                {
                  "type": "string"
                },
                {
                  "type": "null"
                }
              ],
              "title": "Authorization"
            }
          }
        ],
        "requestBody": {
          "required": true,
          "content": {
            "application/json": {
              "schema": {
                "$ref": "#/components/schemas/AssesmentUpdate"
              }
            }
          }
        },
        "responses": {
          "200": {
            "description": "Successful Response",
            "content": {
              "application/json": {
                "schema": {
                  "$ref": "#/components/schemas/Assesment"
                }
              }
            }
          },
          "422": {
            "description": "Validation Error",
            "content": {
              "application/json": {
                "schema": {
                  "$ref": "#/components/schemas/HTTPValidationError"
                }
              }
            }
          }
        }
      },
      "delete": {
        "tags": [
          "assesments"
        ],
        "summary": "Delete Assesment",
        "operationId": "delete_assesment_v1_assesments__id__delete",
        "parameters": [
          {
            "name": "id",
            "in": "path",
            "required": true,
            "schema": {
              "type": "integer",
              "title": "Id"
            }
          },
          {
            "name": "authorization",
            "in": "header",
            "required": false,
            "schema": {
              "anyOf": [
                {
                  "type": "string"
                },
                {
                  "type": "null"
                }
              ],
              "title": "Authorization"
            }
          }
        ],
        "responses": {
          "200": {
            "description": "Successful Response",
            "content": {
              "application/json": {
                "schema": {
                  "type": "object",
                  "additionalProperties": true,
                  "title": "Response Delete Assesment V1 Assesments  Id  Delete"
                }
              }
            }
          },
          "422": {
            "description": "Validation Error",
            "content": {
              "application/json": {
                "schema": {
                  "$ref": "#/components/schemas/HTTPValidationError"
                }
              }
            }
          }
        }
      }
    },
    "/v1/lectures": {
      "get": {
        "tags": [
          "lectures"
        ],
        "summary": "List Lectures",
        "operationId": "list_lectures_v1_lectures_get",
        "parameters": [
          {
            "name": "page",
            "in": "query",
            "required": false,
            "schema": {
              "type": "integer",
              "minimum": 1,
              "default": 1,
              "title": "Page"
            }
          },
          {
            "name": "size",
            "in": "query",
            "required": false,
            "schema": {
              "type": "integer",
              "maximum": 100,
              "default": 20,
              "title": "Size"
            }
          },
          {
            "name": "authorization",
            "in": "header",
            "required": false,
            "schema": {
              "anyOf": [
                {
                  "type": "string"
                },
                {
                  "type": "null"
                }
              ],
              "title": "Authorization"
            }
          }
        ],
        "responses": {
          "200": {
            "description": "Successful Response",
            "content": {
              "application/json": {
                "schema": {
                  "$ref": "#/components/schemas/PaginatedLectures"
                }
              }
            }
          },
          "422": {
            "description": "Validation Error",
            "content": {
              "application/json": {
                "schema": {
                  "$ref": "#/components/schemas/HTTPValidationError"
                }
              }
            }
          }
        }
      },
      "post": {
        "tags": [
          "lectures"
        ],
        "summary": "Create Lecture",
        "operationId": "create_lecture_v1_lectures_post",
        "parameters": [
          {
            "name": "authorization",
            "in": "header",
            "required": false,
            "schema": {
              "anyOf": [
                {
                  "type": "string"
                },
                {
                  "type": "null"
                }
              ],
              "title": "Authorization"
            }
          }
        ],
        "requestBody": {
          "required": true,
          "content": {
            "application/json": {
              "schema": {
                "$ref": "#/components/schemas/LectureCreate"
              }
            }
          }
        },
        "responses": {
          "201": {
            "description": "Successful Response",
            "content": {
              "application/json": {
                "schema": {
                  "$ref": "#/components/schemas/Lecture"
                }
              }
            }
          },
          "422": {
            "description": "Validation Error",
            "content": {
              "application/json": {
                "schema": {
                  "$ref": "#/components/schemas/HTTPValidationError"
                }
              }
            }
          }
        }
      }
    },
    "/v1/lectures/{id}": {
      "get": {
        "tags": [
          "lectures"
        ],
        "summary": "Get Lecture",
        "operationId": "get_lecture_v1_lectures__id__get",
        "parameters": [
          {
            "name": "id",
            "in": "path",
            "required": true,
            "schema": {
              "type": "integer",
              "title": "Id"
            }
          },
          {
            "name": "authorization",
            "in": "header",
            "required": false,
            "schema": {
              "anyOf": [
                {
                  "type": "string"
                },
                {
                  "type": "null"
                }
              ],
              "title": "Authorization"
            }
          }
        ],
        "responses": {
          "200": {
            "description": "Successful Response",
            "content": {
              "application/json": {
                "schema": {
                  "$ref": "#/components/schemas/Lecture"
                }
              }
            }
          },
          "422": {
            "description": "Validation Error",
            "content": {
              "application/json": {
                "schema": {
                  "$ref": "#/components/schemas/HTTPValidationError"
                }
              }
            }
          }
        }
      },
      "put": {
        "tags": [
          "lectures"
        ],
        "summary": "Update Lecture",
        "operationId": "update_lecture_v1_lectures__id__put",
        "parameters": [
          {
            "name": "id",
            "in": "path",
            "required": true,
            "schema": {
              "type": "integer",
              "title": "Id"
            }
          },
          {
            "name": "authorization",
            "in": "header",
            "required": false,
            "schema": {
              "anyOf": [
                {
                  "type": "string"
                },
                {
                  "type": "null"
                }
              ],
              "title": "Authorization"
            }
          }
        ],
        "requestBody": {
          "required": true,
          "content": {
            "application/json": {
              "schema": {
                "$ref": "#/components/schemas/LectureUpdate"
              }
            }
          }
        },
        "responses": {
          "200": {
            "description": "Successful Response",
            "content": {
              "application/json": {
                "schema": {
                  "$ref": "#/components/schemas/Lecture"
                }
              }
            }
          },
          "422": {
            "description": "Validation Error",
            "content": {
              "application/json": {
                "schema": {
                  "$ref": "#/components/schemas/HTTPValidationError"
                }
              }
            }
          }
        }
      },
      "delete": {
        "tags": [
          "lectures"
        ],
        "summary": "Delete Lecture",
        "operationId": "delete_lecture_v1_lectures__id__delete",
        "parameters": [
          {
            "name": "id",
            "in": "path",
            "required": true,
            "schema": {
              "type": "integer",
              "title": "Id"
            }
          },
          {
            "name": "authorization",
            "in": "header",
            "required": false,
            "schema": {
              "anyOf": [
                {
                  "type": "string"
                },
                {
                  "type": "null"
                }
              ],
              "title": "Authorization"
            }
          }
        ],
        "responses": {
          "200": {
            "description": "Successful Response",
            "content": {
              "application/json": {
                "schema": {
                  "type": "object",
                  "additionalProperties": true,
                  "title": "Response Delete Lecture V1 Lectures  Id  Delete"
                }
              }
            }
          },
          "422": {
            "description": "Validation Error",
            "content": {
              "application/json": {
                "schema": {
                  "$ref": "#/components/schemas/HTTPValidationError"
                }
              }
            }
          }
        }
      }
    },
    "/v1/snaptrade/connections": {
      "post": {
        "tags": [
          "snaptrade connections"
        ],
        "summary": "Create Connection",
        "operationId": "create_connection_v1_snaptrade_connections_post",
        "parameters": [
          {
            "name": "authorization",
            "in": "header",
            "required": false,
            "schema": {
              "anyOf": [
                {
                  "type": "string"
                },
                {
                  "type": "null"
                }
              ],
              "title": "Authorization"
            }
          }
        ],
        "requestBody": {
          "required": true,
          "content": {
            "application/json": {
              "schema": {
                "$ref": "#/components/schemas/SnaptradeConnectionCreate"
              }
            }
          }
        },
        "responses": {
          "201": {
            "description": "Successful Response",
            "content": {
              "application/json": {
                "schema": {
                  "$ref": "#/components/schemas/SnaptradeConnection"
                }
              }
            }
          },
          "422": {
            "description": "Validation Error",
            "content": {
              "application/json": {
                "schema": {
                  "$ref": "#/components/schemas/HTTPValidationError"
                }
              }
            }
          }
        }
      }
    },
    "/v1/snaptrade/connections/sync": {
      "get": {
        "tags": [
          "snaptrade connections"
        ],
        "summary": "Sync Connections",
        "operationId": "sync_connections_v1_snaptrade_connections_sync_get",
        "parameters": [
          {
            "name": "authorization",
            "in": "header",
            "required": false,
            "schema": {
              "anyOf": [
                {
                  "type": "string"
                },
                {
                  "type": "null"
                }
              ],
              "title": "Authorization"
            }
          }
        ],
        "responses": {
          "200": {
            "description": "Successful Response",
            "content": {
              "application/json": {
                "schema": {
                  "type": "object",
                  "additionalProperties": true,
                  "title": "Response Sync Connections V1 Snaptrade Connections Sync Get"
                }
              }
            }
          },
          "422": {
            "description": "Validation Error",
            "content": {
              "application/json": {
                "schema": {
                  "$ref": "#/components/schemas/HTTPValidationError"
                }
              }
            }
          }
        }
      }
    },
    "/v1/snaptrade/connections/{id}": {
      "get": {
        "tags": [
          "snaptrade connections"
        ],
        "summary": "Get Connection",
        "operationId": "get_connection_v1_snaptrade_connections__id__get",
        "parameters": [
          {
            "name": "id",
            "in": "path",
            "required": true,
            "schema": {
              "type": "integer",
              "title": "Id"
            }
          },
          {
            "name": "refresh",
            "in": "query",
            "required": false,
            "schema": {
              "type": "boolean",
              "default": false,
              "title": "Refresh"
            }
          },
          {
            "name": "authorization",
            "in": "header",
            "required": false,
            "schema": {
              "anyOf": [
                {
                  "type": "string"
                },
                {
                  "type": "null"
                }
              ],
              "title": "Authorization"
            }
          }
        ],
        "responses": {
          "200": {
            "description": "Successful Response",
            "content": {
              "application/json": {
                "schema": {
                  "$ref": "#/components/schemas/SnaptradeConnection"
                }
              }
            }
          },
          "422": {
            "description": "Validation Error",
            "content": {
              "application/json": {
                "schema": {
                  "$ref": "#/components/schemas/HTTPValidationError"
                }
              }
            }
          }
        }
      },
      "put": {
        "tags": [
          "snaptrade connections"
        ],
        "summary": "Update Connection",
        "operationId": "update_connection_v1_snaptrade_connections__id__put",
        "parameters": [
          {
            "name": "id",
            "in": "path",
            "required": true,
            "schema": {
              "type": "integer",
              "title": "Id"
            }
          },
          {
            "name": "authorization",
            "in": "header",
            "required": false,
            "schema": {
              "anyOf": [
                {
                  "type": "string"
                },
                {
                  "type": "null"
                }
              ],
              "title": "Authorization"
            }
          }
        ],
        "requestBody": {
          "required": true,
          "content": {
            "application/json": {
              "schema": {
                "$ref": "#/components/schemas/SnaptradeConnectionUpdate"
              }
            }
          }
        },
        "responses": {
          "200": {
            "description": "Successful Response",
            "content": {
              "application/json": {
                "schema": {
                  "$ref": "#/components/schemas/SnaptradeConnection"
                }
              }
            }
          },
          "422": {
            "description": "Validation Error",
            "content": {
              "application/json": {
                "schema": {
                  "$ref": "#/components/schemas/HTTPValidationError"
                }
              }
            }
          }
        }
      },
      "delete": {
        "tags": [
          "snaptrade connections"
        ],
        "summary": "Delete Connection",
        "operationId": "delete_connection_v1_snaptrade_connections__id__delete",
        "parameters": [
          {
            "name": "id",
            "in": "path",
            "required": true,
            "schema": {
              "type": "integer",
              "title": "Id"
            }
          },
          {
            "name": "authorization",
            "in": "header",
            "required": false,
            "schema": {
              "anyOf": [
                {
                  "type": "string"
                },
                {
                  "type": "null"
                }
              ],
              "title": "Authorization"
            }
          }
        ],
        "responses": {
          "200": {
            "description": "Successful Response",
            "content": {
              "application/json": {
                "schema": {
                  "type": "object",
                  "additionalProperties": true,
                  "title": "Response Delete Connection V1 Snaptrade Connections  Id  Delete"
                }
              }
            }
          },
          "422": {
            "description": "Validation Error",
            "content": {
              "application/json": {
                "schema": {
                  "$ref": "#/components/schemas/HTTPValidationError"
                }
              }
            }
          }
        }
      }
    },
    "/v1/snaptrade/accounts": {
      "post": {
        "tags": [
          "snaptrade accounts"
        ],
        "summary": "Create Account",
        "operationId": "create_account_v1_snaptrade_accounts_post",
        "parameters": [
          {
            "name": "authorization",
            "in": "header",
            "required": false,
            "schema": {
              "anyOf": [
                {
                  "type": "string"
                },
                {
                  "type": "null"
                }
              ],
              "title": "Authorization"
            }
          }
        ],
        "requestBody": {
          "required": true,
          "content": {
            "application/json": {
              "schema": {
                "$ref": "#/components/schemas/SnaptradeAccountCreate"
              }
            }
          }
        },
        "responses": {
          "201": {
            "description": "Successful Response",
            "content": {
              "application/json": {
                "schema": {
                  "$ref": "#/components/schemas/SnaptradeAccount"
                }
              }
            }
          },
          "422": {
            "description": "Validation Error",
            "content": {
              "application/json": {
                "schema": {
                  "$ref": "#/components/schemas/HTTPValidationError"
                }
              }
            }
          }
        }
      }
    },
    "/v1/snaptrade/accounts/sync": {
      "get": {
        "tags": [
          "snaptrade accounts"
        ],
        "summary": "Sync Accounts",
        "operationId": "sync_accounts_v1_snaptrade_accounts_sync_get",
        "parameters": [
          {
            "name": "authorization",
            "in": "header",
            "required": false,
            "schema": {
              "anyOf": [
                {
                  "type": "string"
                },
                {
                  "type": "null"
                }
              ],
              "title": "Authorization"
            }
          }
        ],
        "responses": {
          "200": {
            "description": "Successful Response",
            "content": {
              "application/json": {
                "schema": {
                  "type": "object",
                  "additionalProperties": true,
                  "title": "Response Sync Accounts V1 Snaptrade Accounts Sync Get"
                }
              }
            }
          },
          "422": {
            "description": "Validation Error",
            "content": {
              "application/json": {
                "schema": {
                  "$ref": "#/components/schemas/HTTPValidationError"
                }
              }
            }
          }
        }
      }
    },
    "/v1/snaptrade/accounts/{id}": {
      "get": {
        "tags": [
          "snaptrade accounts"
        ],
        "summary": "Get Account",
        "operationId": "get_account_v1_snaptrade_accounts__id__get",
        "parameters": [
          {
            "name": "id",
            "in": "path",
            "required": true,
            "schema": {
              "type": "integer",
              "title": "Id"
            }
          },
          {
            "name": "refresh",
            "in": "query",
            "required": false,
            "schema": {
              "type": "boolean",
              "default": false,
              "title": "Refresh"
            }
          },
          {
            "name": "authorization",
            "in": "header",
            "required": false,
            "schema": {
              "anyOf": [
                {
                  "type": "string"
                },
                {
                  "type": "null"
                }
              ],
              "title": "Authorization"
            }
          }
        ],
        "responses": {
          "200": {
            "description": "Successful Response",
            "content": {
              "application/json": {
                "schema": {
                  "$ref": "#/components/schemas/SnaptradeAccount"
                }
              }
            }
          },
          "422": {
            "description": "Validation Error",
            "content": {
              "application/json": {
                "schema": {
                  "$ref": "#/components/schemas/HTTPValidationError"
                }
              }
            }
          }
        }
      },
      "put": {
        "tags": [
          "snaptrade accounts"
        ],
        "summary": "Update Account",
        "operationId": "update_account_v1_snaptrade_accounts__id__put",
        "parameters": [
          {
            "name": "id",
            "in": "path",
            "required": true,
            "schema": {
              "type": "integer",
              "title": "Id"
            }
          },
          {
            "name": "authorization",
            "in": "header",
            "required": false,
            "schema": {
              "anyOf": [
                {
                  "type": "string"
                },
                {
                  "type": "null"
                }
              ],
              "title": "Authorization"
            }
          }
        ],
        "requestBody": {
          "required": true,
          "content": {
            "application/json": {
              "schema": {
                "$ref": "#/components/schemas/SnaptradeAccountUpdate"
              }
            }
          }
        },
        "responses": {
          "200": {
            "description": "Successful Response",
            "content": {
              "application/json": {
                "schema": {
                  "$ref": "#/components/schemas/SnaptradeAccount"
                }
              }
            }
          },
          "422": {
            "description": "Validation Error",
            "content": {
              "application/json": {
                "schema": {
                  "$ref": "#/components/schemas/HTTPValidationError"
                }
              }
            }
          }
        }
      },
      "delete": {
        "tags": [
          "snaptrade accounts"
        ],
        "summary": "Delete Account",
        "operationId": "delete_account_v1_snaptrade_accounts__id__delete",
        "parameters": [
          {
            "name": "id",
            "in": "path",
            "required": true,
            "schema": {
              "type": "integer",
              "title": "Id"
            }
          },
          {
            "name": "authorization",
            "in": "header",
            "required": false,
            "schema": {
              "anyOf": [
                {
                  "type": "string"
                },
                {
                  "type": "null"
                }
              ],
              "title": "Authorization"
            }
          }
        ],
        "responses": {
          "200": {
            "description": "Successful Response",
            "content": {
              "application/json": {
                "schema": {
                  "type": "object",
                  "additionalProperties": true,
                  "title": "Response Delete Account V1 Snaptrade Accounts  Id  Delete"
                }
              }
            }
          },
          "422": {
            "description": "Validation Error",
            "content": {
              "application/json": {
                "schema": {
                  "$ref": "#/components/schemas/HTTPValidationError"
                }
              }
            }
          }
        }
      }
    },
    "/v1/snaptrade/auth/connection-portal": {
      "get": {
        "tags": [
          "snaptrade auth"
        ],
        "summary": "Get Connection Portal",
        "operationId": "get_connection_portal_v1_snaptrade_auth_connection_portal_get",
        "parameters": [
          {
            "name": "authorization",
            "in": "header",
            "required": false,
            "schema": {
              "anyOf": [
                {
                  "type": "string"
                },
                {
                  "type": "null"
                }
              ],
              "title": "Authorization"
            }
          }
        ],
        "responses": {
          "200": {
            "description": "Successful Response",
            "content": {
              "application/json": {
                "schema": {
                  "type": "string",
                  "title": "Response Get Connection Portal V1 Snaptrade Auth Connection Portal Get"
                }
              }
            }
          },
          "422": {
            "description": "Validation Error",
            "content": {
              "application/json": {
                "schema": {
                  "$ref": "#/components/schemas/HTTPValidationError"
                }
              }
            }
          }
        }
      }
    },
    "/v1/plaid/items": {
      "post": {
        "tags": [
          "plaid items"
        ],
        "summary": "Create Item",
        "operationId": "create_item_v1_plaid_items_post",
        "parameters": [
          {
            "name": "authorization",
            "in": "header",
            "required": false,
            "schema": {
              "anyOf": [
                {
                  "type": "string"
                },
                {
                  "type": "null"
                }
              ],
              "title": "Authorization"
            }
          }
        ],
        "requestBody": {
          "required": true,
          "content": {
            "application/json": {
              "schema": {
                "$ref": "#/components/schemas/PlaidItemCreate"
              }
            }
          }
        },
        "responses": {
          "201": {
            "description": "Successful Response",
            "content": {
              "application/json": {
                "schema": {
                  "$ref": "#/components/schemas/PlaidItem"
                }
              }
            }
          },
          "422": {
            "description": "Validation Error",
            "content": {
              "application/json": {
                "schema": {
                  "$ref": "#/components/schemas/HTTPValidationError"
                }
              }
            }
          }
        }
      }
    },
    "/v1/plaid/items/sync": {
      "get": {
        "tags": [
          "plaid items"
        ],
        "summary": "Sync Items",
        "operationId": "sync_items_v1_plaid_items_sync_get",
        "parameters": [
          {
            "name": "authorization",
            "in": "header",
            "required": false,
            "schema": {
              "anyOf": [
                {
                  "type": "string"
                },
                {
                  "type": "null"
                }
              ],
              "title": "Authorization"
            }
          }
        ],
        "responses": {
          "200": {
            "description": "Successful Response",
            "content": {
              "application/json": {
                "schema": {
                  "type": "object",
                  "additionalProperties": true,
                  "title": "Response Sync Items V1 Plaid Items Sync Get"
                }
              }
            }
          },
          "422": {
            "description": "Validation Error",
            "content": {
              "application/json": {
                "schema": {
                  "$ref": "#/components/schemas/HTTPValidationError"
                }
              }
            }
          }
        }
      }
    },
    "/v1/plaid/items/{id}": {
      "get": {
        "tags": [
          "plaid items"
        ],
        "summary": "Get Item",
        "operationId": "get_item_v1_plaid_items__id__get",
        "parameters": [
          {
            "name": "id",
            "in": "path",
            "required": true,
            "schema": {
              "type": "integer",
              "title": "Id"
            }
          },
          {
            "name": "refresh",
            "in": "query",
            "required": false,
            "schema": {
              "type": "boolean",
              "default": false,
              "title": "Refresh"
            }
          },
          {
            "name": "authorization",
            "in": "header",
            "required": false,
            "schema": {
              "anyOf": [
                {
                  "type": "string"
                },
                {
                  "type": "null"
                }
              ],
              "title": "Authorization"
            }
          }
        ],
        "responses": {
          "200": {
            "description": "Successful Response",
            "content": {
              "application/json": {
                "schema": {
                  "$ref": "#/components/schemas/PlaidItem"
                }
              }
            }
          },
          "422": {
            "description": "Validation Error",
            "content": {
              "application/json": {
                "schema": {
                  "$ref": "#/components/schemas/HTTPValidationError"
                }
              }
            }
          }
        }
      },
      "put": {
        "tags": [
          "plaid items"
        ],
        "summary": "Update Item",
        "operationId": "update_item_v1_plaid_items__id__put",
        "parameters": [
          {
            "name": "id",
            "in": "path",
            "required": true,
            "schema": {
              "type": "integer",
              "title": "Id"
            }
          },
          {
            "name": "authorization",
            "in": "header",
            "required": false,
            "schema": {
              "anyOf": [
                {
                  "type": "string"
                },
                {
                  "type": "null"
                }
              ],
              "title": "Authorization"
            }
          }
        ],
        "requestBody": {
          "required": true,
          "content": {
            "application/json": {
              "schema": {
                "$ref": "#/components/schemas/PlaidItemUpdate"
              }
            }
          }
        },
        "responses": {
          "200": {
            "description": "Successful Response",
            "content": {
              "application/json": {
                "schema": {
                  "$ref": "#/components/schemas/PlaidItem"
                }
              }
            }
          },
          "422": {
            "description": "Validation Error",
            "content": {
              "application/json": {
                "schema": {
                  "$ref": "#/components/schemas/HTTPValidationError"
                }
              }
            }
          }
        }
      },
      "delete": {
        "tags": [
          "plaid items"
        ],
        "summary": "Delete Item",
        "operationId": "delete_item_v1_plaid_items__id__delete",
        "parameters": [
          {
            "name": "id",
            "in": "path",
            "required": true,
            "schema": {
              "type": "integer",
              "title": "Id"
            }
          },
          {
            "name": "authorization",
            "in": "header",
            "required": false,
            "schema": {
              "anyOf": [
                {
                  "type": "string"
                },
                {
                  "type": "null"
                }
              ],
              "title": "Authorization"
            }
          }
        ],
        "responses": {
          "200": {
            "description": "Successful Response",
            "content": {
              "application/json": {
                "schema": {
                  "type": "object",
                  "additionalProperties": true,
                  "title": "Response Delete Item V1 Plaid Items  Id  Delete"
                }
              }
            }
          },
          "422": {
            "description": "Validation Error",
            "content": {
              "application/json": {
                "schema": {
                  "$ref": "#/components/schemas/HTTPValidationError"
                }
              }
            }
          }
        }
      }
    },
    "/v1/plaid/accounts": {
      "post": {
        "tags": [
          "plaid accounts"
        ],
        "summary": "Create Account",
        "operationId": "create_account_v1_plaid_accounts_post",
        "parameters": [
          {
            "name": "authorization",
            "in": "header",
            "required": false,
            "schema": {
              "anyOf": [
                {
                  "type": "string"
                },
                {
                  "type": "null"
                }
              ],
              "title": "Authorization"
            }
          }
        ],
        "requestBody": {
          "required": true,
          "content": {
            "application/json": {
              "schema": {
                "$ref": "#/components/schemas/PlaidAccountCreate"
              }
            }
          }
        },
        "responses": {
          "201": {
            "description": "Successful Response",
            "content": {
              "application/json": {
                "schema": {
                  "$ref": "#/components/schemas/PlaidAccount"
                }
              }
            }
          },
          "422": {
            "description": "Validation Error",
            "content": {
              "application/json": {
                "schema": {
                  "$ref": "#/components/schemas/HTTPValidationError"
                }
              }
            }
          }
        }
      }
    },
    "/v1/plaid/accounts/sync": {
      "get": {
        "tags": [
          "plaid accounts"
        ],
        "summary": "Sync Accounts",
        "operationId": "sync_accounts_v1_plaid_accounts_sync_get",
        "parameters": [
          {
            "name": "authorization",
            "in": "header",
            "required": false,
            "schema": {
              "anyOf": [
                {
                  "type": "string"
                },
                {
                  "type": "null"
                }
              ],
              "title": "Authorization"
            }
          }
        ],
        "responses": {
          "200": {
            "description": "Successful Response",
            "content": {
              "application/json": {
                "schema": {
                  "type": "object",
                  "additionalProperties": true,
                  "title": "Response Sync Accounts V1 Plaid Accounts Sync Get"
                }
              }
            }
          },
          "422": {
            "description": "Validation Error",
            "content": {
              "application/json": {
                "schema": {
                  "$ref": "#/components/schemas/HTTPValidationError"
                }
              }
            }
          }
        }
      }
    },
    "/v1/plaid/accounts/{id}": {
      "get": {
        "tags": [
          "plaid accounts"
        ],
        "summary": "Get Account",
        "operationId": "get_account_v1_plaid_accounts__id__get",
        "parameters": [
          {
            "name": "id",
            "in": "path",
            "required": true,
            "schema": {
              "type": "integer",
              "title": "Id"
            }
          },
          {
            "name": "refresh",
            "in": "query",
            "required": false,
            "schema": {
              "type": "boolean",
              "default": false,
              "title": "Refresh"
            }
          },
          {
            "name": "authorization",
            "in": "header",
            "required": false,
            "schema": {
              "anyOf": [
                {
                  "type": "string"
                },
                {
                  "type": "null"
                }
              ],
              "title": "Authorization"
            }
          }
        ],
        "responses": {
          "200": {
            "description": "Successful Response",
            "content": {
              "application/json": {
                "schema": {
                  "$ref": "#/components/schemas/PlaidAccount"
                }
              }
            }
          },
          "422": {
            "description": "Validation Error",
            "content": {
              "application/json": {
                "schema": {
                  "$ref": "#/components/schemas/HTTPValidationError"
                }
              }
            }
          }
        }
      },
      "put": {
        "tags": [
          "plaid accounts"
        ],
        "summary": "Update Account",
        "operationId": "update_account_v1_plaid_accounts__id__put",
        "parameters": [
          {
            "name": "id",
            "in": "path",
            "required": true,
            "schema": {
              "type": "integer",
              "title": "Id"
            }
          },
          {
            "name": "authorization",
            "in": "header",
            "required": false,
            "schema": {
              "anyOf": [
                {
                  "type": "string"
                },
                {
                  "type": "null"
                }
              ],
              "title": "Authorization"
            }
          }
        ],
        "requestBody": {
          "required": true,
          "content": {
            "application/json": {
              "schema": {
                "$ref": "#/components/schemas/PlaidAccountUpdate"
              }
            }
          }
        },
        "responses": {
          "200": {
            "description": "Successful Response",
            "content": {
              "application/json": {
                "schema": {
                  "$ref": "#/components/schemas/PlaidAccount"
                }
              }
            }
          },
          "422": {
            "description": "Validation Error",
            "content": {
              "application/json": {
                "schema": {
                  "$ref": "#/components/schemas/HTTPValidationError"
                }
              }
            }
          }
        }
      },
      "delete": {
        "tags": [
          "plaid accounts"
        ],
        "summary": "Delete Account",
        "operationId": "delete_account_v1_plaid_accounts__id__delete",
        "parameters": [
          {
            "name": "id",
            "in": "path",
            "required": true,
            "schema": {
              "type": "integer",
              "title": "Id"
            }
          },
          {
            "name": "authorization",
            "in": "header",
            "required": false,
            "schema": {
              "anyOf": [
                {
                  "type": "string"
                },
                {
                  "type": "null"
                }
              ],
              "title": "Authorization"
            }
          }
        ],
        "responses": {
          "200": {
            "description": "Successful Response",
            "content": {
              "application/json": {
                "schema": {
                  "type": "object",
                  "additionalProperties": true,
                  "title": "Response Delete Account V1 Plaid Accounts  Id  Delete"
                }
              }
            }
          },
          "422": {
            "description": "Validation Error",
            "content": {
              "application/json": {
                "schema": {
                  "$ref": "#/components/schemas/HTTPValidationError"
                }
              }
            }
          }
        }
      }
    },
    "/v1/plaid/auth/link-token": {
      "get": {
        "tags": [
          "plaid auth"
        ],
        "summary": "Get Link Token",
        "operationId": "get_link_token_v1_plaid_auth_link_token_get",
        "parameters": [
          {
            "name": "authorization",
            "in": "header",
            "required": false,
            "schema": {
              "anyOf": [
                {
                  "type": "string"
                },
                {
                  "type": "null"
                }
              ],
              "title": "Authorization"
            }
          }
        ],
        "responses": {
          "200": {
            "description": "Successful Response",
            "content": {
              "application/json": {
                "schema": {
                  "type": "string",
                  "title": "Response Get Link Token V1 Plaid Auth Link Token Get"
                }
              }
            }
          },
          "422": {
            "description": "Validation Error",
            "content": {
              "application/json": {
                "schema": {
                  "$ref": "#/components/schemas/HTTPValidationError"
                }
              }
            }
          }
        }
      }
    },
    "/v1/plaid/auth/exchange-public-token": {
      "post": {
        "tags": [
          "plaid auth"
        ],
        "summary": "Exchange Public Token",
        "operationId": "exchange_public_token_v1_plaid_auth_exchange_public_token_post",
        "parameters": [
          {
            "name": "authorization",
            "in": "header",
            "required": false,
            "schema": {
              "anyOf": [
                {
                  "type": "string"
                },
                {
                  "type": "null"
                }
              ],
              "title": "Authorization"
            }
          }
        ],
        "requestBody": {
          "required": true,
          "content": {
            "application/json": {
              "schema": {
                "type": "string",
                "title": "Public Token"
              }
            }
          }
        },
        "responses": {
          "200": {
            "description": "Successful Response",
            "content": {
              "application/json": {
                "schema": {
                  "$ref": "#/components/schemas/PlaidItem"
                }
              }
            }
          },
          "422": {
            "description": "Validation Error",
            "content": {
              "application/json": {
                "schema": {
                  "$ref": "#/components/schemas/HTTPValidationError"
                }
              }
            }
          }
        }
      }
    },
    "/health": {
      "get": {
        "tags": [
          "health"
        ],
        "summary": "Health",
        "operationId": "health_health_get",
        "responses": {
          "200": {
            "description": "Successful Response",
            "content": {
              "application/json": {
                "schema": {
                  "additionalProperties": {
                    "type": "string"
                  },
                  "type": "object",
                  "title": "Response Health Health Get"
                }
              }
            }
          }
        }
      }
    }
  },
  "components": {
    "schemas": {
      "Assesment": {
        "properties": {
          "id": {
            "anyOf": [
              {
                "type": "integer"
              },
              {
                "type": "null"
              }
            ],
            "title": "Id"
          },
          "course_id": {
            "type": "integer",
            "title": "Course Id"
          },
          "name": {
            "type": "string",
            "title": "Name"
          },
          "description": {
            "type": "string",
            "title": "Description"
          },
          "type": {
            "type": "string",
            "title": "Type"
          },
          "start_date": {
            "type": "string",
            "format": "date-time",
            "title": "Start Date"
          },
          "end_date": {
            "type": "string",
            "format": "date-time",
            "title": "End Date"
          },
          "weight": {
            "type": "number",
            "title": "Weight"
          },
          "final_grade": {
            "type": "number",
            "title": "Final Grade"
          },
          "created_at": {
            "type": "string",
            "format": "date-time",
            "title": "Created At"
          },
          "updated_at": {
            "type": "string",
            "format": "date-time",
            "title": "Updated At"
          }
        },
        "type": "object",
        "required": [
          "course_id",
          "name",
          "description",
          "type",
          "start_date",
          "end_date",
          "weight",
          "final_grade"
        ],
        "title": "Assesment"
      },
      "AssesmentCreate": {
        "properties": {
          "course_id": {
            "type": "integer",
            "title": "Course Id"
          },
          "name": {
            "type": "string",
            "title": "Name"
          },
          "description": {
            "type": "string",
            "title": "Description"
          },
          "type": {
            "type": "string",
            "title": "Type"
          },
          "start_date": {
            "type": "string",
            "format": "date-time",
            "title": "Start Date"
          },
          "end_date": {
            "type": "string",
            "format": "date-time",
            "title": "End Date"
          },
          "weight": {
            "type": "number",
            "title": "Weight"
          },
          "final_grade": {
            "type": "number",
            "title": "Final Grade"
          }
        },
        "type": "object",
        "required": [
          "course_id",
          "name",
          "description",
          "type",
          "start_date",
          "end_date",
          "weight",
          "final_grade"
        ],
        "title": "AssesmentCreate"
      },
      "AssesmentUpdate": {
        "properties": {
          "course_id": {
            "type": "integer",
            "title": "Course Id"
          },
          "name": {
            "type": "string",
            "title": "Name"
          },
          "description": {
            "type": "string",
            "title": "Description"
          },
          "type": {
            "type": "string",
            "title": "Type"
          },
          "start_date": {
            "type": "string",
            "format": "date-time",
            "title": "Start Date"
          },
          "end_date": {
            "type": "string",
            "format": "date-time",
            "title": "End Date"
          },
          "weight": {
            "type": "number",
            "title": "Weight"
          },
          "final_grade": {
            "type": "number",
            "title": "Final Grade"
          }
        },
        "type": "object",
        "required": [
          "course_id",
          "name",
          "description",
          "type",
          "start_date",
          "end_date",
          "weight",
          "final_grade"
        ],
        "title": "AssesmentUpdate"
      },
      "Course": {
        "properties": {
          "id": {
            "anyOf": [
              {
                "type": "integer"
              },
              {
                "type": "null"
              }
            ],
            "title": "Id"
          },
          "name": {
            "type": "string",
            "title": "Name"
          },
          "description": {
            "type": "string",
            "title": "Description"
          },
          "code": {
            "type": "string",
            "title": "Code"
          },
          "professor_name": {
            "type": "string",
            "title": "Professor Name"
          },
          "professor_email": {
            "type": "string",
            "title": "Professor Email"
          },
          "credits": {
            "type": "integer",
            "title": "Credits"
          },
          "semester": {
            "type": "string",
            "title": "Semester"
          },
          "year": {
            "type": "integer",
            "title": "Year"
          },
          "department": {
            "type": "string",
            "title": "Department"
          },
          "campus": {
            "type": "string",
            "title": "Campus"
          },
          "location": {
            "type": "string",
            "title": "Location"
          },
          "final_grade": {
            "type": "number",
            "title": "Final Grade"
          },
          "created_at": {
            "type": "string",
            "format": "date-time",
            "title": "Created At"
          },
          "updated_at": {
            "type": "string",
            "format": "date-time",
            "title": "Updated At"
          }
        },
        "type": "object",
        "required": [
          "name",
          "description",
          "code",
          "professor_name",
          "professor_email",
          "credits",
          "semester",
          "year",
          "department",
          "campus",
          "location",
          "final_grade"
        ],
        "title": "Course"
      },
      "CourseCreate": {
        "properties": {
          "name": {
            "type": "string",
            "title": "Name"
          },
          "description": {
            "type": "string",
            "title": "Description"
          },
          "code": {
            "type": "string",
            "title": "Code"
          },
          "professor_name": {
            "type": "string",
            "title": "Professor Name"
          },
          "professor_email": {
            "type": "string",
            "title": "Professor Email"
          },
          "credits": {
            "type": "integer",
            "title": "Credits"
          },
          "semester": {
            "type": "string",
            "title": "Semester"
          },
          "year": {
            "type": "integer",
            "title": "Year"
          },
          "department": {
            "type": "string",
            "title": "Department"
          },
          "campus": {
            "type": "string",
            "title": "Campus"
          },
          "location": {
            "type": "string",
            "title": "Location"
          },
          "final_grade": {
            "type": "number",
            "title": "Final Grade"
          }
        },
        "type": "object",
        "required": [
          "name",
          "description",
          "code",
          "professor_name",
          "professor_email",
          "credits",
          "semester",
          "year",
          "department",
          "campus",
          "location",
          "final_grade"
        ],
        "title": "CourseCreate"
      },
      "CourseUpdate": {
        "properties": {
          "name": {
            "type": "string",
            "title": "Name"
          },
          "description": {
            "type": "string",
            "title": "Description"
          },
          "code": {
            "type": "string",
            "title": "Code"
          },
          "professor_name": {
            "type": "string",
            "title": "Professor Name"
          },
          "professor_email": {
            "type": "string",
            "title": "Professor Email"
          },
          "credits": {
            "type": "integer",
            "title": "Credits"
          },
          "semester": {
            "type": "string",
            "title": "Semester"
          },
          "year": {
            "type": "integer",
            "title": "Year"
          },
          "department": {
            "type": "string",
            "title": "Department"
          },
          "campus": {
            "type": "string",
            "title": "Campus"
          },
          "location": {
            "type": "string",
            "title": "Location"
          },
          "final_grade": {
            "type": "number",
            "title": "Final Grade"
          }
        },
        "type": "object",
        "required": [
          "name",
          "description",
          "code",
          "professor_name",
          "professor_email",
          "credits",
          "semester",
          "year",
          "department",
          "campus",
          "location",
          "final_grade"
        ],
        "title": "CourseUpdate"
      },
      "HTTPValidationError": {
        "properties": {
          "detail": {
            "items": {
              "$ref": "#/components/schemas/ValidationError"
            },
            "type": "array",
            "title": "Detail"
          }
        },
        "type": "object",
        "title": "HTTPValidationError"
      },
      "Lecture": {
        "properties": {
          "id": {
            "anyOf": [
              {
                "type": "integer"
              },
              {
                "type": "null"
              }
            ],
            "title": "Id"
          },
          "course_id": {
            "type": "integer",
            "title": "Course Id"
          },
          "name": {
            "type": "string",
            "title": "Name"
          },
          "description": {
            "type": "string",
            "title": "Description"
          },
          "start_date": {
            "type": "string",
            "format": "date-time",
            "title": "Start Date"
          },
          "end_date": {
            "type": "string",
            "format": "date-time",
            "title": "End Date"
          },
          "weight": {
            "type": "number",
            "title": "Weight"
          },
          "final_grade": {
            "type": "number",
            "title": "Final Grade"
          },
          "created_at": {
            "type": "string",
            "format": "date-time",
            "title": "Created At"
          },
          "updated_at": {
            "type": "string",
            "format": "date-time",
            "title": "Updated At"
          }
        },
        "type": "object",
        "required": [
          "course_id",
          "name",
          "description",
          "start_date",
          "end_date",
          "weight",
          "final_grade"
        ],
        "title": "Lecture"
      },
      "LectureCreate": {
        "properties": {
          "course_id": {
            "type": "integer",
            "title": "Course Id"
          },
          "name": {
            "type": "string",
            "minLength": 3,
            "title": "Name"
          },
          "description": {
            "type": "string",
            "minLength": 3,
            "title": "Description"
          },
          "start_date": {
            "type": "string",
            "minLength": 3,
            "format": "date-time",
            "title": "Start Date"
          },
          "end_date": {
            "type": "string",
            "minLength": 3,
            "format": "date-time",
            "title": "End Date"
          },
          "weight": {
            "type": "number",
            "minLength": 3,
            "title": "Weight"
          },
          "final_grade": {
            "type": "number",
            "minLength": 3,
            "title": "Final Grade"
          }
        },
        "type": "object",
        "required": [
          "course_id",
          "name",
          "description",
          "start_date",
          "end_date",
          "weight",
          "final_grade"
        ],
        "title": "LectureCreate"
      },
      "LectureUpdate": {
        "properties": {
          "course_id": {
            "type": "integer",
            "title": "Course Id"
          },
          "name": {
            "type": "string",
            "minLength": 3,
            "title": "Name"
          },
          "description": {
            "type": "string",
            "minLength": 3,
            "title": "Description"
          },
          "start_date": {
            "type": "string",
            "minLength": 3,
            "format": "date-time",
            "title": "Start Date"
          },
          "end_date": {
            "type": "string",
            "minLength": 3,
            "format": "date-time",
            "title": "End Date"
          },
          "weight": {
            "type": "number",
            "minLength": 3,
            "title": "Weight"
          },
          "final_grade": {
            "type": "number",
            "minLength": 3,
            "title": "Final Grade"
          }
        },
        "type": "object",
        "required": [
          "course_id",
          "name",
          "description",
          "start_date",
          "end_date",
          "weight",
          "final_grade"
        ],
        "title": "LectureUpdate"
      },
      "PaginatedAssesments": {
        "properties": {
          "items": {
            "items": {
              "$ref": "#/components/schemas/Assesment"
            },
            "type": "array",
            "title": "Items"
          },
          "page": {
            "type": "integer",
            "title": "Page"
          },
          "size": {
            "type": "integer",
            "title": "Size"
          },
          "total": {
            "type": "integer",
            "title": "Total"
          }
        },
        "type": "object",
        "required": [
          "items",
          "page",
          "size",
          "total"
        ],
        "title": "PaginatedAssesments"
      },
      "PaginatedCourses": {
        "properties": {
          "items": {
            "items": {
              "$ref": "#/components/schemas/Course"
            },
            "type": "array",
            "title": "Items"
          },
          "page": {
            "type": "integer",
            "title": "Page"
          },
          "size": {
            "type": "integer",
            "title": "Size"
          },
          "total": {
            "type": "integer",
            "title": "Total"
          }
        },
        "type": "object",
        "required": [
          "items",
          "page",
          "size",
          "total"
        ],
        "title": "PaginatedCourses"
      },
      "PaginatedLectures": {
        "properties": {
          "items": {
            "items": {
              "$ref": "#/components/schemas/Lecture"
            },
            "type": "array",
            "title": "Items"
          },
          "page": {
            "type": "integer",
            "title": "Page"
          },
          "size": {
            "type": "integer",
            "title": "Size"
          },
          "total": {
            "type": "integer",
            "title": "Total"
          }
        },
        "type": "object",
        "required": [
          "items",
          "page",
          "size",
          "total"
        ],
        "title": "PaginatedLectures"
      },
      "PaginatedUsers": {
        "properties": {
          "items": {
            "items": {
              "$ref": "#/components/schemas/User"
            },
            "type": "array",
            "title": "Items"
          },
          "page": {
            "type": "integer",
            "title": "Page"
          },
          "size": {
            "type": "integer",
            "title": "Size"
          },
          "total": {
            "type": "integer",
            "title": "Total"
          }
        },
        "type": "object",
        "required": [
          "items",
          "page",
          "size",
          "total"
        ],
        "title": "PaginatedUsers"
      },
      "PlaidAccount": {
        "properties": {
          "id": {
            "anyOf": [
              {
                "type": "integer"
              },
              {
                "type": "null"
              }
            ],
            "title": "Id"
          },
          "clerk_user_id": {
            "type": "string",
            "title": "Clerk User Id"
          },
          "account_id": {
            "type": "string",
            "title": "Account Id"
          },
          "name": {
            "type": "string",
            "title": "Name"
          },
          "official_name": {
            "type": "string",
            "title": "Official Name"
          },
          "type": {
            "type": "string",
            "title": "Type"
          },
          "subtype": {
            "type": "string",
            "title": "Subtype"
          },
          "current_balance": {
            "type": "number",
            "title": "Current Balance"
          },
          "available_balance": {
            "type": "number",
            "title": "Available Balance"
          },
          "iso_currency_code": {
            "type": "string",
            "title": "Iso Currency Code"
          },
          "mask": {
            "type": "string",
            "title": "Mask"
          },
          "created_at": {
            "type": "string",
            "format": "date-time",
            "title": "Created At"
          },
          "updated_at": {
            "type": "string",
            "format": "date-time",
            "title": "Updated At"
          }
        },
        "type": "object",
        "required": [
          "clerk_user_id",
          "account_id",
          "name",
          "official_name",
          "type",
          "subtype",
          "current_balance",
          "available_balance",
          "iso_currency_code",
          "mask"
        ],
        "title": "PlaidAccount"
      },
      "PlaidAccountCreate": {
        "properties": {
          "clerk_user_id": {
            "type": "string",
            "title": "Clerk User Id"
          },
          "account_id": {
            "type": "string",
            "title": "Account Id"
          },
          "name": {
            "type": "string",
            "title": "Name"
          },
          "official_name": {
            "type": "string",
            "title": "Official Name"
          },
          "type": {
            "type": "string",
            "title": "Type"
          },
          "subtype": {
            "type": "string",
            "title": "Subtype"
          },
          "current_balance": {
            "type": "number",
            "title": "Current Balance"
          },
          "available_balance": {
            "type": "number",
            "title": "Available Balance"
          },
          "iso_currency_code": {
            "type": "string",
            "title": "Iso Currency Code"
          },
          "mask": {
            "type": "string",
            "title": "Mask"
          }
        },
        "type": "object",
        "required": [
          "clerk_user_id",
          "account_id",
          "name",
          "official_name",
          "type",
          "subtype",
          "current_balance",
          "available_balance",
          "iso_currency_code",
          "mask"
        ],
        "title": "PlaidAccountCreate"
      },
      "PlaidAccountUpdate": {
        "properties": {
          "clerk_user_id": {
            "type": "string",
            "title": "Clerk User Id"
          },
          "account_id": {
            "type": "string",
            "title": "Account Id"
          },
          "name": {
            "type": "string",
            "title": "Name"
          },
          "official_name": {
            "type": "string",
            "title": "Official Name"
          },
          "type": {
            "type": "string",
            "title": "Type"
          },
          "subtype": {
            "type": "string",
            "title": "Subtype"
          },
          "current_balance": {
            "type": "number",
            "title": "Current Balance"
          },
          "available_balance": {
            "type": "number",
            "title": "Available Balance"
          },
          "iso_currency_code": {
            "type": "string",
            "title": "Iso Currency Code"
          },
          "mask": {
            "type": "string",
            "title": "Mask"
          }
        },
        "type": "object",
        "required": [
          "clerk_user_id",
          "account_id",
          "name",
          "official_name",
          "type",
          "subtype",
          "current_balance",
          "available_balance",
          "iso_currency_code",
          "mask"
        ],
        "title": "PlaidAccountUpdate"
      },
      "PlaidItem": {
        "properties": {
          "id": {
            "anyOf": [
              {
                "type": "integer"
              },
              {
                "type": "null"
              }
            ],
            "title": "Id"
          },
          "clerk_user_id": {
            "type": "string",
            "title": "Clerk User Id"
          },
          "item_id": {
            "type": "string",
            "title": "Item Id"
          },
          "access_token": {
            "type": "string",
            "title": "Access Token"
          },
          "institution_name": {
            "type": "string",
            "title": "Institution Name"
          },
          "created_at": {
            "type": "string",
            "format": "date-time",
            "title": "Created At"
          },
          "updated_at": {
            "type": "string",
            "format": "date-time",
            "title": "Updated At"
          }
        },
        "type": "object",
        "required": [
          "clerk_user_id",
          "item_id",
          "access_token",
          "institution_name"
        ],
        "title": "PlaidItem"
      },
      "PlaidItemCreate": {
        "properties": {
          "clerk_user_id": {
            "type": "string",
            "title": "Clerk User Id"
          },
          "item_id": {
            "type": "string",
            "title": "Item Id"
          },
          "access_token": {
            "type": "string",
            "title": "Access Token"
          },
          "institution_name": {
            "type": "string",
            "title": "Institution Name"
          }
        },
        "type": "object",
        "required": [
          "clerk_user_id",
          "item_id",
          "access_token"
        ],
        "title": "PlaidItemCreate"
      },
      "PlaidItemUpdate": {
        "properties": {
          "clerk_user_id": {
            "type": "string",
            "title": "Clerk User Id"
          },
          "item_id": {
            "type": "string",
            "title": "Item Id"
          },
          "access_token": {
            "type": "string",
            "title": "Access Token"
          },
          "institution_name": {
            "type": "string",
            "title": "Institution Name"
          }
        },
        "type": "object",
        "required": [
          "clerk_user_id",
          "item_id",
          "access_token"
        ],
        "title": "PlaidItemUpdate"
      },
      "SnaptradeAccount": {
        "properties": {
          "id": {
            "anyOf": [
              {
                "type": "integer"
              },
              {
                "type": "null"
              }
            ],
            "title": "Id"
          },
          "clerk_user_id": {
            "type": "string",
            "title": "Clerk User Id"
          },
          "account_id": {
            "type": "string",
            "title": "Account Id"
          },
          "connection_id": {
            "type": "string",
            "title": "Connection Id"
          },
          "name": {
            "type": "string",
            "title": "Name"
          },
          "number": {
            "type": "string",
            "title": "Number"
          },
          "institution_name": {
            "type": "string",
            "title": "Institution Name"
          },
          "status": {
            "type": "string",
            "title": "Status"
          },
          "type": {
            "type": "string",
            "title": "Type"
          },
          "current_balance": {
            "type": "number",
            "title": "Current Balance"
          },
          "currency": {
            "type": "string",
            "title": "Currency"
          },
          "updated_at": {
            "type": "string",
            "format": "date-time",
            "title": "Updated At"
          },
          "created_at": {
            "type": "string",
            "format": "date-time",
            "title": "Created At"
          }
        },
        "type": "object",
        "required": [
          "clerk_user_id",
          "account_id",
          "connection_id",
          "name",
          "number",
          "institution_name",
          "status",
          "type",
          "current_balance",
          "currency"
        ],
        "title": "SnaptradeAccount"
      },
      "SnaptradeAccountCreate": {
        "properties": {
          "clerk_user_id": {
            "type": "string",
            "title": "Clerk User Id"
          },
          "account_id": {
            "type": "string",
            "title": "Account Id"
          },
          "connection_id": {
            "type": "string",
            "title": "Connection Id"
          },
          "name": {
            "type": "string",
            "title": "Name"
          },
          "number": {
            "type": "string",
            "title": "Number"
          },
          "institution_name": {
            "type": "string",
            "title": "Institution Name"
          },
          "status": {
            "type": "string",
            "title": "Status"
          },
          "type": {
            "type": "string",
            "title": "Type"
          },
          "current_balance": {
            "type": "number",
            "title": "Current Balance"
          },
          "currency": {
            "type": "string",
            "title": "Currency"
          }
        },
        "type": "object",
        "required": [
          "clerk_user_id",
          "account_id",
          "connection_id",
          "name",
          "number",
          "institution_name",
          "status",
          "type",
          "current_balance",
          "currency"
        ],
        "title": "SnaptradeAccountCreate"
      },
      "SnaptradeAccountUpdate": {
        "properties": {
          "clerk_user_id": {
            "type": "string",
            "title": "Clerk User Id"
          },
          "account_id": {
            "type": "string",
            "title": "Account Id"
          },
          "connection_id": {
            "type": "string",
            "title": "Connection Id"
          },
          "name": {
            "type": "string",
            "title": "Name"
          },
          "number": {
            "type": "string",
            "title": "Number"
          },
          "institution_name": {
            "type": "string",
            "title": "Institution Name"
          },
          "status": {
            "type": "string",
            "title": "Status"
          },
          "type": {
            "type": "string",
            "title": "Type"
          },
          "current_balance": {
            "type": "number",
            "title": "Current Balance"
          },
          "currency": {
            "type": "string",
            "title": "Currency"
          }
        },
        "type": "object",
        "required": [
          "clerk_user_id",
          "account_id",
          "connection_id",
          "name",
          "number",
          "institution_name",
          "status",
          "type",
          "current_balance",
          "currency"
        ],
        "title": "SnaptradeAccountUpdate"
      },
      "SnaptradeConnection": {
        "properties": {
          "id": {
            "anyOf": [
              {
                "type": "integer"
              },
              {
                "type": "null"
              }
            ],
            "title": "Id"
          },
          "clerk_user_id": {
            "type": "string",
            "title": "Clerk User Id"
          },
          "user_secret": {
            "type": "string",
            "title": "User Secret"
          },
          "connection_id": {
            "type": "string",
            "title": "Connection Id"
          },
          "brokerage_name": {
            "type": "string",
            "title": "Brokerage Name"
          },
          "updated_at": {
            "type": "string",
            "format": "date-time",
            "title": "Updated At"
          },
          "created_at": {
            "type": "string",
            "format": "date-time",
            "title": "Created At"
          }
        },
        "type": "object",
        "required": [
          "clerk_user_id",
          "user_secret",
          "connection_id",
          "brokerage_name"
        ],
        "title": "SnaptradeConnection"
      },
      "SnaptradeConnectionCreate": {
        "properties": {
          "clerk_user_id": {
            "type": "string",
            "title": "Clerk User Id"
          },
          "connection_id": {
            "type": "string",
            "title": "Connection Id"
          },
          "user_secret": {
            "anyOf": [
              {
                "type": "string"
              },
              {
                "type": "null"
              }
            ],
            "title": "User Secret"
          },
          "brokerage_name": {
            "anyOf": [
              {
                "type": "string"
              },
              {
                "type": "null"
              }
            ],
            "title": "Brokerage Name"
          }
        },
        "type": "object",
        "required": [
          "clerk_user_id",
          "connection_id"
        ],
        "title": "SnaptradeConnectionCreate"
      },
      "SnaptradeConnectionUpdate": {
        "properties": {
          "clerk_user_id": {
            "type": "string",
            "title": "Clerk User Id"
          },
          "connection_id": {
            "type": "string",
            "title": "Connection Id"
          },
          "user_secret": {
            "anyOf": [
              {
                "type": "string"
              },
              {
                "type": "null"
              }
            ],
            "title": "User Secret"
          },
          "brokerage_name": {
            "anyOf": [
              {
                "type": "string"
              },
              {
                "type": "null"
              }
            ],
            "title": "Brokerage Name"
          }
        },
        "type": "object",
        "required": [
          "clerk_user_id",
          "connection_id"
        ],
        "title": "SnaptradeConnectionUpdate"
      },
      "User": {
        "properties": {
          "id": {
            "anyOf": [
              {
                "type": "integer"
              },
              {
                "type": "null"
              }
            ],
            "title": "Id"
          },
          "clerk_user_id": {
            "type": "string",
            "title": "Clerk User Id"
          },
          "email": {
            "type": "string",
            "title": "Email"
          },
          "first_name": {
            "type": "string",
            "title": "First Name"
          },
          "last_name": {
            "type": "string",
            "title": "Last Name"
          },
          "phone": {
            "type": "string",
            "title": "Phone"
          },
          "created_at": {
            "type": "string",
            "format": "date-time",
            "title": "Created At"
          },
          "updated_at": {
            "type": "string",
            "format": "date-time",
            "title": "Updated At"
          }
        },
        "type": "object",
        "required": [
          "clerk_user_id",
          "email",
          "first_name",
          "last_name",
          "phone"
        ],
        "title": "User"
      },
      "UserUpdate": {
        "properties": {
          "email": {
            "type": "string",
            "minLength": 3,
            "title": "Email"
          },
          "first_name": {
            "type": "string",
            "minLength": 3,
            "title": "First Name"
          },
          "last_name": {
            "type": "string",
            "minLength": 3,
            "title": "Last Name"
          },
          "phone": {
            "type": "string",
            "minLength": 3,
            "title": "Phone"
          }
        },
        "type": "object",
        "required": [
          "email",
          "first_name",
          "last_name",
          "phone"
        ],
        "title": "UserUpdate"
      },
      "ValidationError": {
        "properties": {
          "loc": {
            "items": {
              "anyOf": [
                {
                  "type": "string"
                },
                {
                  "type": "integer"
                }
              ]
            },
            "type": "array",
            "title": "Location"
          },
          "msg": {
            "type": "string",
            "title": "Message"
          },
          "type": {
            "type": "string",
            "title": "Error Type"
          }
        },
        "type": "object",
        "required": [
          "loc",
          "msg",
          "type"
        ],
        "title": "ValidationError"
      }
    }
  }
}